ent/__init__.py
ent/consts.py
ent/core.py
ent/utils.py
monlycee-1.0.dist-info/LICENSE
monlycee-1.0.dist-info/METADATA
monlycee-1.0.dist-info/WHEEL
monlycee-1.0.dist-info/top_level.txt
monlycee-1.0.dist-info/RECORD
