Metadata-Version: 2.1
Name: monlycee
Version: 1.0
Summary: An API ent.iledefrance.fr
Home-page: https://github.com/Egsagon/monlycee-net-api
Author: Egsagon
Author-email: egsagon12@gmail.com
License: GPL-3.0
Platform: unix
Platform: linux
Platform: win32
Platform: cygwin
Classifier: Development Status :: 4 - Beta
Classifier: License :: OSI Approved :: MIT License
Classifier: Programming Language :: Python :: 3.11
Requires-Python: >=3.11
License-File: LICENSE
Requires-Dist: requests (>=2)
Requires-Dist: beautifulsoup4 (>=4)
